musi/init.py
musi/main.py
musi_piacode-0.1.0.dist-info/METADATA
musi_piacode-0.1.0.dist-info/WHEEL
musi_piacode-0.1.0.dist-info/top_level.txt
musi_piacode-0.1.0.dist-info/RECORD
