Metadata-Version: 2.4
Name: musi-piacode
Version: 0.1.0
Summary: A music package based on the twelve-tone equal temperament
Author-email: piacode <liangzanqun@163.com>
Classifier: Programming Language :: Python :: 3
Classifier: License :: OSI Approved :: MIT License
Classifier: Operating System :: OS Independent
Requires-Python: >=3.7
Requires-Dist: numpy==1.26.4
Requires-Dist: pydub==0.25.1
